{"transcript":"ˈœyt.ɣəˌɦɑŋ.ə(n)","exists":true,"definitions":["Zijn opgehangen (van iets dat buiten hangt, zoals wasgoed of een vlag).","Tijd doorbrengen op een informele manier, rondhangen.","Zich vertonen, zich laten zien (vaak in een openbare ruimte)."],"examples":["De was is uitgehangen om te drogen.","Ze hebben de hele middag in het park uitgehangen.","Hij heeft zich de laatste tijd veel in die kroeg uitgehangen."],"lemma":"uithangen","lemmaPos":"verb","synonyms":["rondhangen","vertoeven","rondlummelen"],"number":"plural","pastTenses":"hing uit, heeft uitgehangen","tense":"past","isIrregular":true,"source":"uitgehangen"}