{"transcript":"ˈplɛnsə(n)","exists":true,"definitions":["Met een plons in het water vallen of iets in het water laten vallen","Spatten, morsen met vloeistof","Overvloedig gieten of regenen"],"examples":["De kinderen plensen in de plas.","Hij plensde water over de rand van het bad.","Het begon te plensen van de regen."],"lemma":"plensen","lemmaPos":"verb","synonyms":["spatten","klotsen","gieten"],"number":"plural","pastTenses":"plensde, heeft geplensd","tense":"present","isIrregular":false,"source":"plensen"}