{"transcript":"ˈɑf.ɣə.voːrt","exists":true,"definitions":["Weggebracht of verwijderd, vaak met betrekking tot afval, mensen of materialen.","Vervoerd naar een andere locatie, bijvoorbeeld naar een ziekenhuis of politiebureau.","Uitgeschakeld of buiten gebruik gesteld."],"examples":["Het afval werd snel afgevoerd.","De gewonde persoon is afgevoerd naar het ziekenhuis.","Oude machines werden afgevoerd en vervangen."],"lemma":"afvoeren","lemmaPos":"verb","synonyms":["wegvoeren","verwijderen","transporteren","wegbrengen"],"number":"singular","pastTenses":"voerde af, heeft afgevoerd","tense":"past","isIrregular":false,"source":"afgevoerd"}