{"transcript":"oːvəˈreːnkoːmə(n)","exists":true,"definitions":["Het eens worden over iets","Overeenstemmen met iets","Een afspraak maken"],"examples":["Zij konden niet overeenkomen over de prijs.","De resultaten komen overeen met onze verwachtingen.","Laten we een datum overeenkomen voor de vergadering."],"lemma":"overeenkomen","lemmaPos":"verb","synonyms":["afspreken","accorderen","matchen"],"number":"plural","pastTenses":"kwam overeen, zijn overeengekomen","tense":"present","isIrregular":true,"source":"overeenkomen"}