{"transcript":"təˈrʏxˌxaːt","exists":true,"definitions":["Gaat terug in de tijd of naar een eerdere plaats.","Keert terug naar een oorspronkelijke staat of positie.","Verwijst naar een eerdere periode of gebeurtenis."],"examples":["De geschiedenis van dit gebouw teruggaat tot de middeleeuwen.","Als de bal teruggaat naar de speler, kan hij opnieuw schieten.","De traditie teruggaat op een oud ritueel."],"lemma":"teruggaan","lemmaPos":"verb","synonyms":["retourneert","keert terug","dateert van"],"number":"singular","pastTenses":"ging terug, is teruggegaan","tense":"present","isIrregular":true,"source":"teruggaat"}