{"transcript":"ˌɔpsɛrˈveːrə(n)","exists":true,"definitions":["Waarnemen, bekijken met aandacht","Gadeslaan, in de gaten houden","Onderzoeken, bestuderen"],"examples":["De wetenschappers observeren het gedrag van de dieren.","Hij observeerde de situatie aandachtig.","We zullen de ontwikkelingen nauwkeurig observeren."],"lemma":"observeren","lemmaPos":"verb","synonyms":["waarnemen","gadeslaan","bekijken","bestuderen"],"number":"plural","pastTenses":"observeerde, heeft geobserveerd","tense":"present","isIrregular":false,"source":"observeren"}