{"transcript":"bəˈɦɑndəldə","exists":true,"definitions":["Voerde een behandeling uit op iets of iemand.","Ging om met iets of iemand op een bepaalde manier.","Besprak een onderwerp of kwestie."],"examples":["De arts behandelde de patiënt met zorg.","Hij behandelde zijn boeken altijd voorzichtig.","De commissie behandelde de klacht snel."],"lemma":"behandelen","lemmaPos":"verb","synonyms":["verzorgde","ging om met","besprak"],"number":"singular","pastTenses":"behandelde, heeft behandeld","tense":"past","isIrregular":false,"source":"behandelde"}