{"transcript":"vərˈveːlə(n)","exists":true,"definitions":["Zich ongemakkelijk voelen door gebrek aan interessante bezigheden.","Iemand anders ongemakkelijk maken door gebrek aan interessante bezigheden."],"examples":["Ik verveel me.","Het verveelt me.","Zij vervelen zich nooit.","Dat verveelt snel."],"lemma":"vervelen","lemmaPos":"verb","synonyms":["ergeren","vervelen","vervelen"],"number":"singular","pastTenses":"verveelde, heeft verveeld","tense":"present","isIrregular":false,"source":"vervelen"}