{"transcript":"ˈtɪkə(n)","exists":true,"definitions":["Licht slaan of aanraken","Typen op een toetsenbord","Een tikkend geluid maken (zoals een klok)","Iemand aantikken om aandacht te trekken"],"examples":["Hij tikte zachtjes op de deur.","Zij is de hele dag aan het tikken op haar laptop.","De klok bleef maar tikken.","Ik tikte hem op zijn schouder."],"lemma":"tikken","lemmaPos":"verb","synonyms":["aantikken","typen","kloppen","aanslaan"],"number":"plural","pastTenses":"tikten, hebben getikt","tense":"present","isIrregular":false,"source":"tikken"}