{"transcript":"ˈɪnˌleːvərə(n)","exists":true,"definitions":["Iets afgeven of teruggeven, vaak aan een autoriteit of voor beoordeling.","Minder worden, afnemen (informeel)."],"examples":["De studenten moeten hun werk morgen inleveren.","Je moet je boeken bij de bibliotheek inleveren.","Hij moest zijn rijbewijs inleveren na het ongeval.","De kwaliteit van het product is ingeleverd."],"lemma":"inleveren","lemmaPos":"verb","synonyms":["afgeven","teruggeven","indienen","overhandigen"],"number":"plural","pastTenses":"leverde in, heeft ingeleverd","tense":"present","isIrregular":false,"source":"inleveren"}