{"source":"personages","number":"plural","lemma":"personage","lemmaPos":"noun","definitions":["Fictieve of historische figuren in verhalen of dramatische werken","Individuen met een bepaalde rol of functie in een bepaalde context","Mensen als subject in schilderkunst of beeldhouwkunst"],"examples":["De roman bevat diverse interessante personages.","De personages in het toneelstuk waren goed uitgewerkt.","De film bracht de personages geloofwaardig tot leven."],"synonyms":["figuur","karakter","rol"],"transcript":"pɛrˈsoːnaːʒəs","gender":"common"}