{"transcript":"ˈoːpə(n)ˌbrekə(n)","exists":true,"definitions":["Met geweld openen, forceren","Een einde maken aan een situatie of overeenkomst","Beginnen te breken of te barsten"],"examples":["De inbrekers probeerden de kluis open te breken.","We moeten de onderhandelingen openbreken om tot een oplossing te komen.","Het ijs begint open te breken."],"lemma":"openbreken","lemmaPos":"verb","synonyms":["forceren","openwrikken","doorbreken"],"number":"singular","pastTenses":"brak open, heeft opengebroken","tense":"present","isIrregular":true,"source":"openbreken"}