{"transcript":"ˈʏpdeːtə(n)","exists":true,"definitions":["Het bijwerken van informatie of gegevens.","Het voorzien van de nieuwste versie van software of een systeem.","Het op de hoogte brengen van de laatste ontwikkelingen."],"examples":["Ik moet de software updaten.","Zij updatet haar profiel regelmatig.","We zullen u op de hoogte houden met updates."],"lemma":"updaten","lemmaPos":"verb","synonyms":["bijwerken","actualiseren","moderniseren"],"number":"singular","pastTenses":"update, heeft geüpdatet","tense":"present","isIrregular":false,"source":"update"}