{"transcript":"ˈbraːdə(n)","exists":true,"definitions":["Het gaar maken van voedsel, meestal vlees, door het te verhitten in vet of olie in een pan of oven.","Het roosteren van iets boven open vuur of onder een grill."],"examples":["Zij zal het vlees braden.","Hij is aan het braden.","Wij braden de aardappelen."],"lemma":"braden","lemmaPos":"verb","synonyms":["roosteren","bakken","frituren"],"number":"singular","pastTenses":"braadde, heeft gebraden","tense":"present","isIrregular":false,"source":"braden"}