{"transcript":"proˈjɛktə(n)","exists":true,"definitions":["Het plannen, organiseren en uitvoeren van projecten","Het ontwerpen en realiseren van projecten","Het beheren van projecten"],"examples":["Zij projecten de bouw van een nieuwe school.","Wij projecten de ontwikkeling van software.","De afdeling projecten de renovatie van het gebouw."],"lemma":"projecteren","lemmaPos":"verb","synonyms":["plannen","ontwerpen","uitvoeren","realiseren"],"number":"plural","pastTenses":"projecteerde, heeft geprojecteerd","tense":"present","isIrregular":false,"source":"projecten"}