{"transcript":"bəɡəˈlɛit","exists":true,"definitions":["Leiden of vergezellen van iemand of iets","Ondersteunen of bijstaan","Muzikaal ondersteunen"],"examples":["Hij begeleid de groep door het museum.","De therapeut begeleid de patiënt bij zijn herstel.","De pianist begeleid de zangeres."],"lemma":"begeleiden","lemmaPos":"verb","synonyms":["vergezellen","bijstaan","ondersteunen"],"number":"singular","pastTenses":"begeleidde, heeft begeleid","tense":"present","isIrregular":false,"source":"begeleid"}