{"transcript":"ˈɔndərˌsxɛit","exists":true,"definitions":["Het vermogen om verschillen te zien of te maken tussen dingen.","Een verschil of onderscheid dat wordt gemaakt.","Het maken van een onderscheid of het herkennen van verschillen."],"examples":["Hij maakt geen onderscheid tussen de twee opties.","Er is een duidelijk onderscheid tussen theorie en praktijk.","Zij kan goed onderscheid maken tussen feiten en meningen."],"lemma":"onderscheiden","lemmaPos":"verb","synonyms":["onderscheiden","differentieëren","onderscheiden"],"number":"singular","pastTenses":"onderscheidde, heeft onderscheiden","tense":"present","isIrregular":true,"source":"onderscheid"}