{"transcript":"traːˈseːrə(n)","exists":true,"definitions":["De oorsprong of locatie van iets achterhalen.","Iets volgen of opsporen.","De loop van iets bepalen."],"examples":["De politie kon de dief traceren.","Het is moeilijk om de bron van het lek te traceren.","We moeten de route van de kabel traceren."],"lemma":"traceren","lemmaPos":"verb","synonyms":["opsporen","achterhalen","volgen","lokaliseren"],"number":"singular","pastTenses":"traceerde, heeft getraceerd","tense":"present","isIrregular":false,"source":"traceren"}