{"transcript":"təˈrʏxzin","exists":true,"definitions":["Iets of iemand opnieuw zien, vaak na een periode van afwezigheid of in een herhaling.","Terugkijken op iets in het verleden, vaak met een bepaalde emotie of evaluatie.","Een herhaling van een programma bekijken."],"examples":["Ik hoop je snel terug te zien.","We zullen terugzien op een mooie tijd.","Kunnen we die aflevering terugzien?"],"lemma":"terugzien","lemmaPos":"verb","synonyms":["herzien","weerzien","overdenken"],"number":"singular","pastTenses":"zag terug, heeft teruggezien","tense":"present","isIrregular":true,"source":"terugzien"}