{"transcript":"ˈɑf.ɣəˌvyːrt","exists":true,"definitions":["Van een wapen: een projectiel lanceren.","Van een raket: lanceren.","Van een vraag of opmerking: snel stellen of maken."],"examples":["Het kanon heeft een schot afgevuurd.","De raket werd succesvol afgevuurd.","Hij heeft een reeks vragen afgevuurd op de spreker."],"lemma":"afvuren","lemmaPos":"verb","synonyms":["schieten","lanceren","afschieten"],"number":"singular","pastTenses":"vuurde af, heeft afgevuurd","tense":"past","isIrregular":false,"source":"afgevuurd"}