{"source":"zwaargewicht","number":"singular","lemma":"zwaargewicht","lemmaPos":"noun","definitions":["persoon of zaak met groot gewicht; wordt ook figuurlijk gebruikt voor een belangrijke of invloedrijke persoon of zaak","gewichtsklasse in de bokssport voor boksers die meer wegen dan de maximale limiet voor het lichte zwaargewicht"],"examples":["Hij is een zwaargewicht in de muziekwereld.","Ze bevinden zich in de zwaargewicht-categorie."],"synonyms":["kolos","gigant"],"transcript":"ˈzʋaːr.ɣəˌʋɪxt","gender":"common"}