{"transcript":"ˈɑftrɛkə(n)","exists":true,"definitions":["Van een totaalbedrag of hoeveelheid verminderen","Een conclusie trekken uit feiten","Masturberen (informeel)"],"examples":["Je moet de kosten aftrekken van de opbrengst.","Uit zijn gedrag kun je veel aftrekken.","Hij zat stiekem af te trekken."],"lemma":"aftrekken","lemmaPos":"verb","synonyms":["verminderen","deduceren","masturberen"],"number":"singular","pastTenses":"trok af, heeft afgetrokken","tense":"present","isIrregular":true,"source":"aftrekken"}