{"transcript":"ˈlɑstɪχˌvɑlən","exists":true,"definitions":["Iemand hinderen of storen","Iemand ongewenst benaderen of last bezorgen","Pesterijen uitoefenen op iemand"],"examples":["Hij probeert haar niet te lastigvallen.","Zij werden lastiggevallen door de menigte.","Zal ik je later lastigvallen?"],"lemma":"lastigvallen","lemmaPos":"verb","synonyms":["hinderen","storen","pesten","ergeren"],"number":"plural","pastTenses":"viel lastig, heeft lastiggevallen","tense":"present","isIrregular":true,"source":"lastigvallen"}