{"transcript":"ˈspaːrdə","exists":true,"definitions":["Verleden tijd enkelvoud van sparen (geld opzijleggen)","Verleden tijd enkelvoud van sparen (bezuinigen)","Verleden tijd enkelvoud van sparen (ontzien)"],"examples":["Hij spaarde elke cent.","Zij spaarde op de boodschappen.","De rechter spaarde de verdachte niet."],"lemma":"sparen","lemmaPos":"verb","synonyms":["bezuinigen","opslaan","ontzien"],"number":"singular","pastTenses":"spaarde, heeft gespaard","tense":"past","isIrregular":false,"source":"spaarde"}