{"transcript":"vərˈvoert","exists":true,"definitions":["Van de ene plaats naar de andere gebracht","Getransporteerd","In een staat van grote emotie gebracht"],"examples":["De goederen werden per schip vervoerd.","Hij was vervoerd door de muziek.","Patiënten worden met ambulances vervoerd."],"lemma":"vervoeren","lemmaPos":"verb","synonyms":["transporteren","overbrengen","bezorgen"],"number":"singular","pastTenses":"vervoerde, heeft vervoerd","tense":"past","isIrregular":false,"source":"vervoerd"}