{"transcript":"ˈʋɪndə(n)","exists":true,"definitions":["Iets om iets anders heen draaien of wikkelen","Opwinden, bijvoorbeeld een klok of speelgoed","Zich snel en kronkelend bewegen","Gas laten ontsnappen uit het lichaam (scheten laten)"],"examples":["Hij windt de draad om de spoel.","Kun je de klok even winden?","De slang windt zich om de tak.","Het kind moest lachen toen hij een wind liet."],"lemma":"winden","lemmaPos":"verb","synonyms":["wikkelen","draaien","opwinden","kronkelen"],"number":"plural","pastTenses":"wond, heeft gewonden","tense":"present","isIrregular":true,"source":"winden"}