{"transcript":"eːlimiˈneːrə(n)","exists":true,"definitions":["Verwijderen of uitsluiten","Wegnemen, buiten beschouwing laten","Doden (in de context van een tegenstander)"],"examples":["De fout moet geëlimineerd worden.","Zij elimineerden hun concurrenten.","De verdachte werd geëlimineerd."],"lemma":"elimineren","lemmaPos":"verb","synonyms":["verwijderen","uitsluiten","wegnemen","uitroeien"],"number":"singular","pastTenses":"elimineerde, heeft geëlimineerd","tense":"present","isIrregular":false,"source":"elimineren"}