{"transcript":"ɑfɣəˈstɛmt","exists":true,"definitions":["In overeenstemming gebracht met iets anders","Aangepast aan een bepaalde situatie of doel","Geregeld of georganiseerd in relatie tot iets"],"examples":["De planning is afgestemd op de beschikbare middelen.","Haar verwachtingen waren niet afgestemd op de realiteit.","De instrumenten zijn nauwkeurig afgestemd."],"lemma":"afstemmen","lemmaPos":"verb","synonyms":["aanpassen","regelen","coördineren"],"number":"singular","pastTenses":"stemde af, heeft afgestemd","tense":"past","isIrregular":false,"source":"afgestemd"}