{"transcript":"ˈʋiɣə(n)","exists":true,"definitions":["Een baby of klein kind zachtjes heen en weer bewegen om het in slaap te krijgen of te kalmeren.","Het gewicht van iets bepalen met een weegschaal.","Zachtjes heen en weer bewegen, schommelen."],"examples":["Zij wiegen de baby in slaap.","De bakker wiegt het brood.","De boot wiegt op de golven."],"lemma":"wiegen","lemmaPos":"verb","synonyms":["schommelen","wegen","deinen"],"number":"plural","pastTenses":"woog, heeft gewogen","tense":"present","isIrregular":true,"source":"wiegen"}