{"transcript":"ˈsmeːrə(n)","exists":true,"definitions":["Een dunne laag van een substantie aanbrengen op een oppervlak.","Iets glad of werkend maken met vet of olie.","Iemand omkopen, steekpenningen geven.","Snel en onzorgvuldig schrijven of tekenen."],"examples":["Hij moet zijn brood smeren.","De monteur zal de ketting smeren.","De ambtenaar liet zich smeren.","Ze begon snel wat aantekeningen te smeren."],"lemma":"smeren","lemmaPos":"verb","synonyms":["insmeren","zalven","oliën","omkopen","schrijven"],"number":"plural","pastTenses":"smeerde, heeft gesmeerd","tense":"present","isIrregular":false,"source":"smeren"}