{"transcript":"ˈdɛŋkə(n)","exists":true,"definitions":["Het proces van het vormen van gedachten of ideeën.","Een mening of overtuiging hebben.","Zich iets herinneren of voorstellen.","Van plan zijn iets te doen."],"examples":["Ik denk aan jou.","Zij denken dat het goed is.","Wij denken erover na.","Wat denk je ervan?"],"lemma":"denken","lemmaPos":"verb","synonyms":["peinzen","overwegen","bedenken","menen"],"number":"plural","pastTenses":"dacht, heeft gedacht","tense":"present","isIrregular":true,"source":"denken"}