{"transcript":"bəˈɑntˌʋoːrdə(n)","exists":true,"definitions":["Antwoord geven op een vraag of bericht.","Reageren op iets.","Voldoen aan iets, overeenkomen met iets."],"examples":["Hij zal de vraag beantwoorden.","Zij beantwoorden de e-mails snel.","De resultaten beantwoorden aan de verwachtingen."],"lemma":"beantwoorden","lemmaPos":"verb","synonyms":["antwoorden","repliek geven","reageren"],"number":"plural","pastTenses":"beantwoordde, heeft beantwoord","tense":"present","isIrregular":false,"source":"beantwoorden"}