{"transcript":"ˈsløːrə(n)","exists":true,"definitions":["Met moeite iets zwaars trekken of meeslepen","Zich met moeite voortbewegen, zich slepend verplaatsen"],"examples":["Hij moest de zware koffer de trap op sleuren.","Ze sleurde zich door de modder.","De kinderen sleuren hun speelgoed over de vloer."],"lemma":"sleuren","lemmaPos":"verb","synonyms":["trekken","meeslepen","voortslepen","zeulen"],"number":"plural","pastTenses":"sleepte, heeft gesleurd","tense":"present","isIrregular":false,"source":"sleuren"}