{"transcript":"breːkt","exists":true,"definitions":["Veroorzaakt dat iets in stukken uiteenvalt","Maakt een einde aan iets","Overtreedt een regel of afspraak","Doet iets plotseling ophouden"],"examples":["Hij breekt het brood.","De zon breekt door de wolken.","Zij breekt haar belofte.","Het geluid breekt de stilte."],"lemma":"breken","lemmaPos":"verb","synonyms":["verbrijzelt","schendt","stopt","vernietigt"],"number":"singular","pastTenses":"brak, heeft gebroken","tense":"present","isIrregular":true,"source":"breekt"}