{"transcript":"ˈsxɪlən","exists":true,"definitions":["De buitenste laag van iets verwijderen, zoals de schil van fruit of groenten.","Verschil maken, onderscheiden (verouderd gebruik)."],"examples":["Ik moet de aardappelen nog schillen.","Zij schilt een appel voor haar kind.","De verf begint te schillen."],"lemma":"schillen","lemmaPos":"verb","synonyms":["pellen","afschillen","afpellen"],"number":"plural","pastTenses":"schilde, heeft geschild","tense":"present","isIrregular":false,"source":"schillen"}