{"transcript":"ˈsxʏdə","exists":true,"definitions":["Verleden tijd enkelvoud van schudden (bewegen, heen en weer bewegen)","Verleden tijd enkelvoud van schudden (doen trillen)","Verleden tijd enkelvoud van schudden (mengen door te schudden)"],"examples":["Hij schudde zijn hoofd.","De aardbeving schudde het gebouw.","Zij schudde de fles voor gebruik."],"lemma":"schudden","lemmaPos":"verb","synonyms":["bewegen","trillen","schokken"],"number":"singular","pastTenses":"schudde, heeft geschud","tense":"past","isIrregular":false,"source":"schudde"}